paradime/__init__.py
paradime/_version.py
paradime/dr.py
paradime/exceptions.py
paradime/loss.py
paradime/models.py
paradime/relationdata.py
paradime/relations.py
paradime/routines.py
paradime/transforms.py
paradime/types.py
paradime/utils/__init__.py
paradime/utils/_cmap.py
paradime/utils/convert.py
paradime/utils/logging.py
paradime/utils/make_palette.py
paradime/utils/palette.json
paradime/utils/palette.svg
paradime/utils/plotting.py
paradime/utils/seed.py
paradime-1.1.0.dist-info/METADATA
paradime-1.1.0.dist-info/WHEEL
paradime-1.1.0.dist-info/licenses/LICENSE
paradime-1.1.0.dist-info/RECORD
