Metadata-Version: 2.1
Name: paradime
Version: 1.1.0
Summary: A framework for parametric dimensionality reduction
Project-URL: Homepage, https://github.com/einbandi/paradime
Project-URL: Bug Tracker, https://github.com/einbandi/paradime/issues
Project-URL: Documentation, https://paradime.readthedocs.io/en/latest/index.html
Author-email: Andreas Hinterreiter <andreas.hinterreiter@jku.at>
License-Expression: MIT
License-File: LICENSE
Classifier: License :: OSI Approved :: MIT License
Classifier: Operating System :: OS Independent
Classifier: Programming Language :: Python :: 3
Requires-Python: >=3.7
Requires-Dist: numpy<1.23,>=1.21
Requires-Dist: pynndescent>=0.5
Requires-Dist: scikit-learn>=1.1
Requires-Dist: scipy>=1.7
